pyfrc/__init__.py
pyfrc/py.typed
pyfrc/util.py
pyfrc/version.py
pyfrc/mains/__init__.py
pyfrc/mains/cli_add_tests.py
pyfrc/mains/cli_coverage.py
pyfrc/mains/cli_create_physics.py
pyfrc/mains/cli_profiler.py
pyfrc/mains/cli_sim.py
pyfrc/mains/cli_test.py
pyfrc/physics/__init__.py
pyfrc/physics/core.py
pyfrc/physics/drivetrains.py
pyfrc/physics/motion.py
pyfrc/physics/motor_cfgs.py
pyfrc/physics/tankmodel.py
pyfrc/physics/units.py
pyfrc/physics/visionsim.py
pyfrc/test_support/__init__.py
pyfrc/test_support/controller.py
pyfrc/test_support/pytest_plugin.py
pyfrc/tests/__init__.py
pyfrc/tests/basic.py
pyfrc/tests/docstring_test.py
pyfrc-2024.0.1.dist-info/LICENSE
pyfrc-2024.0.1.dist-info/METADATA
pyfrc-2024.0.1.dist-info/WHEEL
pyfrc-2024.0.1.dist-info/entry_points.txt
pyfrc-2024.0.1.dist-info/top_level.txt
pyfrc-2024.0.1.dist-info/RECORD
