Metadata-Version: 2.1
Name: pyfrc
Version: 2024.0.1
Summary: Development tools library for python interpreter used for the FIRST Robotics Competition
Home-page: https://github.com/robotpy/pyfrc
Author: Dustin Spicuzza
Author-email: robotpy@googlegroups.com
License: BSD-3-Clause
Classifier: Development Status :: 5 - Production/Stable
Classifier: Intended Audience :: Developers
Classifier: License :: OSI Approved :: BSD License
Classifier: Programming Language :: Python :: 3 :: Only
Classifier: Topic :: Software Development
Classifier: Topic :: Software Development :: Testing
Requires-Python: >=3.8
License-File: LICENSE
Requires-Dist: pytest>=3.9
Requires-Dist: pytest-reraise
Requires-Dist: pint>=0.11.0
Requires-Dist: wpilib<2025,>=2024.1.0
Requires-Dist: robotpy-cli~=2024.0
